gis_fillers/__init__.py
gis_fillers/_version.py
gis_fillers/database.py
gis_fillers/initscript.sql
gis_fillers/fillers/__init__.py
gis_fillers/fillers/fillers.py
gis_fillers/fillers/zones/__init__.py
gis_fillers/fillers/zones/countries.py
gis_fillers/fillers/zones/generic.py
gis_fillers/fillers/zones/hexagons.py
gis_fillers/fillers/zones/zaehlsprengel.py
gis_fillers/getters/__init__.py
gis_fillers/getters/generic_getters.py
gis_fillers/getters/zone_getters.py
gis_fillers-0.0.10.dist-info/LICENSE
gis_fillers-0.0.10.dist-info/METADATA
gis_fillers-0.0.10.dist-info/WHEEL
gis_fillers-0.0.10.dist-info/top_level.txt
gis_fillers-0.0.10.dist-info/RECORD
