Metadata-Version: 2.1
Name: gis-fillers
Version: 0.0.10
Summary: UNKNOWN
Home-page: UNKNOWN
Author: William Schueller
Author-email: UNKNOWN
License: GNU AFFERO GENERAL PUBLIC LICENSE Version 3
Platform: UNKNOWN
Requires-Dist: pyshp
Requires-Dist: psycopg2-binary
Requires-Dist: numpy (>=1.16.5)
Requires-Dist: pandas
Requires-Dist: openpyxl
Requires-Dist: geopandas
Requires-Dist: shapely
Requires-Dist: scipy
Requires-Dist: matplotlib
Requires-Dist: camelot-py[cv]
Requires-Dist: odfpy
Requires-Dist: db-fillers
Requires-Dist: h3
Requires-Dist: topojson
